hctestpro/__init__.py
hctestpro/file_upload.py
hctestpro/image_recognition.py
hctestpro/report_screenshot.py
hctestpro-1.0.0.dist-info/METADATA
hctestpro-1.0.0.dist-info/WHEEL
hctestpro-1.0.0.dist-info/top_level.txt
hctestpro-1.0.0.dist-info/RECORD
